[
  {
    "study_id": "PMID_41013466",
    "any_ae_intervention": 0,
    "any_ae_control": 0,
    "any_ae_intervention_total": null,
    "any_ae_control_total": null,
    "serious_ae_intervention": null,
    "serious_ae_control": null,
    "dropout_intervention": null,
    "dropout_control": null,
    "dropout_intervention_total": null,
    "dropout_control_total": null,
    "specific_aes": "No adverse events were reported."
  },
  {
    "study_id": "PMID_40420669",
    "any_ae_intervention": null,
    "any_ae_control": null,
    "any_ae_intervention_total": 37,
    "any_ae_control_total": 38,
    "serious_ae_intervention": null,
    "serious_ae_control": null,
    "dropout_intervention": null,
    "dropout_control": null,
    "dropout_intervention_total": 37,
    "dropout_control_total": 38,
    "specific_aes": "No specific adverse events were reported in the results section."
  },
  {
    "study_id": "PMID_40838395",
    "any_ae_intervention": null,
    "any_ae_control": null,
    "any_ae_intervention_total": 12,
    "any_ae_control_total": 12,
    "serious_ae_intervention": 0,
    "serious_ae_control": 0,
    "dropout_intervention": null,
    "dropout_control": null,
    "dropout_intervention_total": 14,
    "dropout_control_total": 14,
    "specific_aes": "All patients well tolerated the rTMS treatment, with no reports of major adverse effects."
  },
  {
    "study_id": "PMID_40785301",
    "any_ae_intervention": null,
    "any_ae_control": null,
    "any_ae_intervention_total": 16,
    "any_ae_control_total": 15,
    "serious_ae_intervention": null,
    "serious_ae_control": null,
    "dropout_intervention": 0,
    "dropout_control": 0,
    "dropout_intervention_total": 16,
    "dropout_control_total": 15,
    "specific_aes": "Tolerability was assessed but results were not reported in the text."
  },
  {
    "study_id": "PMID_37608981",
    "any_ae_intervention": null,
    "any_ae_control": null,
    "any_ae_intervention_total": 44,
    "any_ae_control_total": 49,
    "serious_ae_intervention": null,
    "serious_ae_control": null,
    "dropout_intervention": 7,
    "dropout_control": 6,
    "dropout_intervention_total": 44,
    "dropout_control_total": 49,
    "specific_aes": "Not reported"
  },
  {
    "study_id": "PMID_31790015",
    "any_ae_intervention": null,
    "any_ae_control": null,
    "any_ae_intervention_total": 17,
    "any_ae_control_total": 17,
    "serious_ae_intervention": 0,
    "serious_ae_control": 0,
    "dropout_intervention": 0,
    "dropout_control": 0,
    "dropout_intervention_total": 17,
    "dropout_control_total": 17,
    "specific_aes": "itchiness (52.9%), tingling (31.4%), discomfort (13.7%), and a burning sensation (13.7%). There were no significant differences between any of the reported symptoms and stimulation type."
  },
  {
    "study_id": "PMID_39269839",
    "any_ae_intervention": 1,
    "any_ae_control": 1,
    "any_ae_intervention_total": 23,
    "any_ae_control_total": 23,
    "serious_ae_intervention": 0,
    "serious_ae_control": 0,
    "dropout_intervention": 0,
    "dropout_control": 0,
    "dropout_intervention_total": 23,
    "dropout_control_total": 23,
    "specific_aes": "tingling sensation (real group), transient itching (sham group)"
  },
  {
    "study_id": "PMID_40443505",
    "any_ae_intervention": 0,
    "any_ae_control": 0,
    "any_ae_intervention_total": 14,
    "any_ae_control_total": 14,
    "serious_ae_intervention": 0,
    "serious_ae_control": 0,
    "dropout_intervention": null,
    "dropout_control": null,
    "dropout_intervention_total": null,
    "dropout_control_total": null,
    "specific_aes": "no significant adverse effects reported"
  },
  {
    "study_id": "PMID_35250453",
    "any_ae_intervention": 4,
    "any_ae_control": 1,
    "any_ae_intervention_total": 20,
    "any_ae_control_total": 20,
    "serious_ae_intervention": 0,
    "serious_ae_control": 0,
    "dropout_intervention": 0,
    "dropout_control": 0,
    "dropout_intervention_total": 20,
    "dropout_control_total": 20,
    "specific_aes": "tDCS group: skin itching (2), prickling sensation (1), skin redness (1). Sham group: skin itching (1). None of the patients had headache, nausea, insomnia, anxiety, epilepsy, or other adverse reactions."
  },
  {
    "study_id": "PMID_39845447",
    "any_ae_intervention": null,
    "any_ae_control": null,
    "any_ae_intervention_total": 17,
    "any_ae_control_total": 16,
    "serious_ae_intervention": null,
    "serious_ae_control": null,
    "dropout_intervention": null,
    "dropout_control": null,
    "dropout_intervention_total": 17,
    "dropout_control_total": 16,
    "specific_aes": "Headache (rTMS: 2, Sham: 1); Scalp/skin discomfort (rTMS: 2, Sham: 1); Neck pain/stiffness (rTMS: 1, Sham: 0); Fatigue (rTMS: 0, Sham: 1)"
  },
  {
    "study_id": "PMID_38007663",
    "any_ae_intervention": null,
    "any_ae_control": null,
    "any_ae_intervention_total": 9,
    "any_ae_control_total": 9,
    "serious_ae_intervention": null,
    "serious_ae_control": null,
    "dropout_intervention": 0,
    "dropout_control": 0,
    "dropout_intervention_total": 9,
    "dropout_control_total": 9,
    "specific_aes": "Adverse events were not explicitly reported in the text."
  },
  {
    "study_id": "PMID_38155843",
    "any_ae_intervention": 5,
    "any_ae_control": 3,
    "any_ae_intervention_total": 63,
    "any_ae_control_total": 61,
    "serious_ae_intervention": 0,
    "serious_ae_control": 0,
    "dropout_intervention": null,
    "dropout_control": null,
    "dropout_intervention_total": null,
    "dropout_control_total": null,
    "specific_aes": "skin redness and swelling"
  },
  {
    "study_id": "PMID_40878312",
    "any_ae_intervention": 1,
    "any_ae_control": 1,
    "any_ae_intervention_total": 4,
    "any_ae_control_total": 4,
    "serious_ae_intervention": 0,
    "serious_ae_control": 0,
    "dropout_intervention": 0,
    "dropout_control": 1,
    "dropout_intervention_total": 4,
    "dropout_control_total": 4,
    "specific_aes": "One patient in the sham group withdrew due to pain at the stimulation site; one in the active group reported mild headache"
  },
  {
    "study_id": "PMID_31127779",
    "any_ae_intervention": 0,
    "any_ae_control": 0,
    "any_ae_intervention_total": null,
    "any_ae_control_total": null,
    "serious_ae_intervention": null,
    "serious_ae_control": null,
    "dropout_intervention": null,
    "dropout_control": null,
    "dropout_intervention_total": null,
    "dropout_control_total": null,
    "specific_aes": "no adverse effect reported"
  },
  {
    "study_id": "PMID_36137949",
    "any_ae_intervention": null,
    "any_ae_control": null,
    "any_ae_intervention_total": 23,
    "any_ae_control_total": 23,
    "serious_ae_intervention": null,
    "serious_ae_control": null,
    "dropout_intervention": 0,
    "dropout_control": 0,
    "dropout_intervention_total": 23,
    "dropout_control_total": 23,
    "specific_aes": "Not reported"
  },
  {
    "study_id": "PMID_29331848",
    "any_ae_intervention": 8,
    "any_ae_control": null,
    "any_ae_intervention_total": 9,
    "any_ae_control_total": 8,
    "serious_ae_intervention": 0,
    "serious_ae_control": 0,
    "dropout_intervention": 1,
    "dropout_control": 0,
    "dropout_intervention_total": 9,
    "dropout_control_total": 8,
    "specific_aes": "rTMS: discomfort at treatment site (8 events in 6 subjects), shock sensation at treatment site (n=1), shock sensation to eye (2 events in 1 subject), facial twitching (n=1), insomnia (n=1), dizziness upon standing (n=1). Sham: neck discomfort (1 event), ER visit for unrelated wrist pain (1 event)."
  },
  {
    "study_id": "PMID_34762980",
    "any_ae_intervention": 6,
    "any_ae_control": 3,
    "any_ae_intervention_total": 33,
    "any_ae_control_total": 32,
    "serious_ae_intervention": 0,
    "serious_ae_control": 0,
    "dropout_intervention": 2,
    "dropout_control": 3,
    "dropout_intervention_total": 35,
    "dropout_control_total": 35,
    "specific_aes": "headache (Sham: 3, IG: 3); skin discomfort (Sham: 4, IG: 1); eye twitching (Sham: 3, IG: 0)"
  },
  {
    "study_id": "PMID_31285793",
    "any_ae_intervention": null,
    "any_ae_control": null,
    "any_ae_intervention_total": 29,
    "any_ae_control_total": 29,
    "serious_ae_intervention": null,
    "serious_ae_control": null,
    "dropout_intervention": 0,
    "dropout_control": 0,
    "dropout_intervention_total": 29,
    "dropout_control_total": 29,
    "specific_aes": "Two individuals dropped out before randomization due to Dengue and Cancer. No adverse events reported during the intervention phase."
  },
  {
    "study_id": "PMID_36313021",
    "any_ae_intervention": null,
    "any_ae_control": null,
    "any_ae_intervention_total": 15,
    "any_ae_control_total": 12,
    "serious_ae_intervention": 0,
    "serious_ae_control": 0,
    "dropout_intervention": null,
    "dropout_control": null,
    "dropout_intervention_total": 15,
    "dropout_control_total": 12,
    "specific_aes": "No intervention-related serious adverse events occurred."
  },
  {
    "study_id": "PMID_26160997",
    "any_ae_intervention": null,
    "any_ae_control": null,
    "any_ae_intervention_total": null,
    "any_ae_control_total": null,
    "serious_ae_intervention": null,
    "serious_ae_control": null,
    "dropout_intervention": 2,
    "dropout_control": 0,
    "dropout_intervention_total": 17,
    "dropout_control_total": 19,
    "specific_aes": "Not reported in provided text"
  },
  {
    "study_id": "PMID_31555109",
    "any_ae_intervention": null,
    "any_ae_control": null,
    "any_ae_intervention_total": null,
    "any_ae_control_total": null,
    "serious_ae_intervention": 0,
    "serious_ae_control": 0,
    "dropout_intervention": 0,
    "dropout_control": 1,
    "dropout_intervention_total": null,
    "dropout_control_total": null,
    "specific_aes": "no serious adverse events"
  },
  {
    "study_id": "PMID_25449530",
    "any_ae_intervention": 0,
    "any_ae_control": 0,
    "any_ae_intervention_total": 18,
    "any_ae_control_total": 18,
    "serious_ae_intervention": 0,
    "serious_ae_control": 0,
    "dropout_intervention": 0,
    "dropout_control": 0,
    "dropout_intervention_total": 18,
    "dropout_control_total": 18,
    "specific_aes": "no adverse effects were reported"
  },
  {
    "study_id": "PMID_27903289",
    "any_ae_intervention": 0,
    "any_ae_control": 0,
    "any_ae_intervention_total": 8,
    "any_ae_control_total": 8,
    "serious_ae_intervention": 0,
    "serious_ae_control": 0,
    "dropout_intervention": 0,
    "dropout_control": 0,
    "dropout_intervention_total": 8,
    "dropout_control_total": 8,
    "specific_aes": "itching, tingling, headache, burning sensation, and discomfort (none reported)"
  },
  {
    "study_id": "PMID_33679572",
    "any_ae_intervention": 1,
    "any_ae_control": 1,
    "any_ae_intervention_total": 16,
    "any_ae_control_total": 12,
    "serious_ae_intervention": 0,
    "serious_ae_control": 0,
    "dropout_intervention": 0,
    "dropout_control": 2,
    "dropout_intervention_total": 16,
    "dropout_control_total": 14,
    "specific_aes": "Sham: 1 transient headache, 1 acute myocardial infarction (unrelated). Real: 1 intolerance to 120% RMT intensity requiring lowering."
  },
  {
    "study_id": "PMID_31196835",
    "any_ae_intervention": null,
    "any_ae_control": null,
    "any_ae_intervention_total": 12,
    "any_ae_control_total": 8,
    "serious_ae_intervention": null,
    "serious_ae_control": null,
    "dropout_intervention": 1,
    "dropout_control": 1,
    "dropout_intervention_total": 12,
    "dropout_control_total": 8,
    "specific_aes": "Two participants dropped out of the study due to refusal or time conflict of a care giver"
  },
  {
    "study_id": "PMID_33610772",
    "any_ae_intervention": null,
    "any_ae_control": null,
    "any_ae_intervention_total": 19,
    "any_ae_control_total": null,
    "serious_ae_intervention": 1,
    "serious_ae_control": null,
    "dropout_intervention": 4,
    "dropout_control": null,
    "dropout_intervention_total": 19,
    "dropout_control_total": null,
    "specific_aes": "two were not suitable for MRI, one had a flu infection and one was seriously injured before the evaluation"
  },
  {
    "study_id": "PMID_31609693",
    "any_ae_intervention": null,
    "any_ae_control": null,
    "any_ae_intervention_total": 7,
    "any_ae_control_total": 7,
    "serious_ae_intervention": null,
    "serious_ae_control": null,
    "dropout_intervention": 0,
    "dropout_control": 0,
    "dropout_intervention_total": 7,
    "dropout_control_total": 7,
    "specific_aes": "Not reported"
  },
  {
    "study_id": "PMID_30940012",
    "any_ae_intervention": 2,
    "any_ae_control": 0,
    "any_ae_intervention_total": 23,
    "any_ae_control_total": 23,
    "serious_ae_intervention": 0,
    "serious_ae_control": 0,
    "dropout_intervention": 0,
    "dropout_control": 2,
    "dropout_intervention_total": 23,
    "dropout_control_total": 23,
    "specific_aes": "itching, headache, and dizziness"
  },
  {
    "study_id": "PMID_27823981",
    "any_ae_intervention": 2,
    "any_ae_control": 1,
    "any_ae_intervention_total": 17,
    "any_ae_control_total": 13,
    "serious_ae_intervention": 0,
    "serious_ae_control": 0,
    "dropout_intervention": 0,
    "dropout_control": 0,
    "dropout_intervention_total": 17,
    "dropout_control_total": 13,
    "specific_aes": "mild headache and fatigue"
  },
  {
    "study_id": "PMID_26401945",
    "any_ae_intervention": 3,
    "any_ae_control": 0,
    "any_ae_intervention_total": 20,
    "any_ae_control_total": 20,
    "serious_ae_intervention": 0,
    "serious_ae_control": 0,
    "dropout_intervention": 0,
    "dropout_control": 0,
    "dropout_intervention_total": 20,
    "dropout_control_total": 20,
    "specific_aes": "painful scalp sensations (n=3 during IFG stimulation)"
  },
  {
    "study_id": "PMID_26064066",
    "any_ae_intervention": null,
    "any_ae_control": null,
    "any_ae_intervention_total": 11,
    "any_ae_control_total": 11,
    "serious_ae_intervention": 0,
    "serious_ae_control": 0,
    "dropout_intervention": 1,
    "dropout_control": null,
    "dropout_intervention_total": 11,
    "dropout_control_total": 11,
    "specific_aes": "Minor discomfort, minor headaches occasionally described. No symptoms of seizure were observed."
  },
  {
    "study_id": "PMID_18525028",
    "any_ae_intervention": null,
    "any_ae_control": null,
    "any_ae_intervention_total": 10,
    "any_ae_control_total": 10,
    "serious_ae_intervention": null,
    "serious_ae_control": null,
    "dropout_intervention": 0,
    "dropout_control": 0,
    "dropout_intervention_total": 10,
    "dropout_control_total": 10,
    "specific_aes": "No specific adverse events reported; authors note 'no study so far reported complications'."
  },
  {
    "study_id": "PMID_22514525",
    "any_ae_intervention": null,
    "any_ae_control": null,
    "any_ae_intervention_total": null,
    "any_ae_control_total": null,
    "serious_ae_intervention": null,
    "serious_ae_control": null,
    "dropout_intervention": 0,
    "dropout_control": 0,
    "dropout_intervention_total": 8,
    "dropout_control_total": 8,
    "specific_aes": "Not reported"
  },
  {
    "study_id": "PMID_21671144",
    "any_ae_intervention": 0,
    "any_ae_control": 0,
    "any_ae_intervention_total": 15,
    "any_ae_control_total": 15,
    "serious_ae_intervention": 0,
    "serious_ae_control": 0,
    "dropout_intervention": 0,
    "dropout_control": 0,
    "dropout_intervention_total": 15,
    "dropout_control_total": 15,
    "specific_aes": "All the patients tolerated rTMS well without any adverse effects."
  },
  {
    "study_id": "PMID_21840288",
    "any_ae_intervention": 0,
    "any_ae_control": 0,
    "any_ae_intervention_total": 15,
    "any_ae_control_total": 15,
    "serious_ae_intervention": 0,
    "serious_ae_control": 0,
    "dropout_intervention": 0,
    "dropout_control": 0,
    "dropout_intervention_total": 15,
    "dropout_control_total": 15,
    "specific_aes": "All 15 patients tolerated tDCS therapy well and none of them reported adverse effects."
  },
  {
    "study_id": "PMID_24678298",
    "any_ae_intervention": null,
    "any_ae_control": null,
    "any_ae_intervention_total": 12,
    "any_ae_control_total": 12,
    "serious_ae_intervention": null,
    "serious_ae_control": null,
    "dropout_intervention": 0,
    "dropout_control": 0,
    "dropout_intervention_total": 12,
    "dropout_control_total": 12,
    "specific_aes": "Not reported"
  },
  {
    "study_id": "SCOPUS_2-s2.0-105029980285",
    "any_ae_intervention": 0,
    "any_ae_control": 0,
    "any_ae_intervention_total": null,
    "any_ae_control_total": null,
    "serious_ae_intervention": 0,
    "serious_ae_control": 0,
    "dropout_intervention": null,
    "dropout_control": null,
    "dropout_intervention_total": null,
    "dropout_control_total": null,
    "specific_aes": "no adverse effect reported"
  },
  {
    "study_id": "RIS_cochrane_271",
    "any_ae_intervention": null,
    "any_ae_control": null,
    "any_ae_intervention_total": 7,
    "any_ae_control_total": 13,
    "serious_ae_intervention": null,
    "serious_ae_control": null,
    "dropout_intervention": 0,
    "dropout_control": 1,
    "dropout_intervention_total": 7,
    "dropout_control_total": 13,
    "specific_aes": "No participants stopped the trial in the active group. After randomization, one participant in the sham group did it during the trial."
  },
  {
    "study_id": "RIS_cochrane_383",
    "any_ae_intervention": null,
    "any_ae_control": null,
    "any_ae_intervention_total": null,
    "any_ae_control_total": null,
    "serious_ae_intervention": 0,
    "serious_ae_control": 1,
    "dropout_intervention": null,
    "dropout_control": null,
    "dropout_intervention_total": null,
    "dropout_control_total": null,
    "specific_aes": "1 acute myocardial infarction in the sham group"
  },
  {
    "study_id": "RIS_cochrane_418",
    "any_ae_intervention": null,
    "any_ae_control": null,
    "any_ae_intervention_total": null,
    "any_ae_control_total": null,
    "serious_ae_intervention": 0,
    "serious_ae_control": 0,
    "dropout_intervention": null,
    "dropout_control": null,
    "dropout_intervention_total": null,
    "dropout_control_total": null,
    "specific_aes": "Treatment site discomfort was the most common adverse event. None of the subjects had a seizure."
  },
  {
    "study_id": "RIS_cochrane_589",
    "any_ae_intervention": null,
    "any_ae_control": null,
    "any_ae_intervention_total": null,
    "any_ae_control_total": null,
    "serious_ae_intervention": 0,
    "serious_ae_control": 1,
    "dropout_intervention": null,
    "dropout_control": null,
    "dropout_intervention_total": null,
    "dropout_control_total": null,
    "specific_aes": "1 acute myocardial infarction in the sham group"
  },
  {
    "study_id": "RIS_cochrane_598",
    "any_ae_intervention": null,
    "any_ae_control": null,
    "any_ae_intervention_total": null,
    "any_ae_control_total": null,
    "serious_ae_intervention": 0,
    "serious_ae_control": 1,
    "dropout_intervention": null,
    "dropout_control": null,
    "dropout_intervention_total": null,
    "dropout_control_total": null,
    "specific_aes": "1 acute myocardial infarction in the sham group"
  },
  {
    "study_id": "RIS_cochrane_605",
    "any_ae_intervention": 11,
    "any_ae_control": 2,
    "any_ae_intervention_total": 79,
    "any_ae_control_total": 50,
    "serious_ae_intervention": null,
    "serious_ae_control": null,
    "dropout_intervention": null,
    "dropout_control": null,
    "dropout_intervention_total": 79,
    "dropout_control_total": 50,
    "specific_aes": "headache (5.4%), scalp/skin discomfort (3.1%), neck pain/stiffness (1.5%), and fatigue (0.7%)"
  },
  {
    "study_id": "RIS_records 1501-2000_120",
    "any_ae_intervention": 0,
    "any_ae_control": 0,
    "any_ae_intervention_total": 10,
    "any_ae_control_total": 10,
    "serious_ae_intervention": 0,
    "serious_ae_control": 0,
    "dropout_intervention": 0,
    "dropout_control": 0,
    "dropout_intervention_total": 10,
    "dropout_control_total": 10,
    "specific_aes": "Subjects tolerated treatment well. There were no adverse effects associated with a single application of tDCS."
  },
  {
    "study_id": "RIS_records 2001-2495_199",
    "any_ae_intervention": 0,
    "any_ae_control": 0,
    "any_ae_intervention_total": 18,
    "any_ae_control_total": 18,
    "serious_ae_intervention": 0,
    "serious_ae_control": 0,
    "dropout_intervention": 0,
    "dropout_control": 0,
    "dropout_intervention_total": 18,
    "dropout_control_total": 18,
    "specific_aes": "none reported"
  },
  {
    "study_id": "RIS_records 2001-2495_217",
    "any_ae_intervention": null,
    "any_ae_control": null,
    "any_ae_intervention_total": 17,
    "any_ae_control_total": 17,
    "serious_ae_intervention": 0,
    "serious_ae_control": 0,
    "dropout_intervention": 0,
    "dropout_control": 0,
    "dropout_intervention_total": 17,
    "dropout_control_total": 17,
    "specific_aes": "itchiness (52.9%), tingling (31.4%), discomfort (13.7%), and a burning sensation (13.7%) - reported overall across all sessions, no significant differences between stimulation types."
  },
  {
    "study_id": "RIS_records 501-1000_156",
    "any_ae_intervention": null,
    "any_ae_control": null,
    "any_ae_intervention_total": 8,
    "any_ae_control_total": null,
    "serious_ae_intervention": 1,
    "serious_ae_control": null,
    "dropout_intervention": 1,
    "dropout_control": null,
    "dropout_intervention_total": 8,
    "dropout_control_total": null,
    "specific_aes": "minor tiredness; urinary sepsis (1 patient, unrelated to trial)"
  },
  {
    "study_id": "RIS_records 501-1000_293",
    "any_ae_intervention": null,
    "any_ae_control": null,
    "any_ae_intervention_total": 21,
    "any_ae_control_total": 21,
    "serious_ae_intervention": null,
    "serious_ae_control": null,
    "dropout_intervention": 0,
    "dropout_control": 0,
    "dropout_intervention_total": 21,
    "dropout_control_total": 21,
    "specific_aes": "Safety was assessed but specific adverse events were not reported in the abstract."
  }
]